voxidiomatix/__init__.py
voxidiomatix/abstract_translator.py
voxidiomatix/cascade_translator.py
voxidiomatix/direct_translator.py
voxidiomatix/display.py
voxidiomatix/file_handler.py
voxidiomatix/parse.py
voxidiomatix/speech.py
voxidiomatix/train.py
voxidiomatix/translate.py
voxidiomatix/voxidiomatix.py
voxidiomatix-0.1.0.dist-info/LICENSE
voxidiomatix-0.1.0.dist-info/METADATA
voxidiomatix-0.1.0.dist-info/WHEEL
voxidiomatix-0.1.0.dist-info/entry_points.txt
voxidiomatix-0.1.0.dist-info/top_level.txt
voxidiomatix-0.1.0.dist-info/RECORD
