Metadata-Version: 2.1
Name: voxidiomatix
Version: 0.1.0
Summary: Speech-to-Speech Multilangual Vocal Translator
Home-page: https://github.com/ClementHuber/voxidiomatix
Author: Clement HUBER
Author-email: clement.victor.huber@gmail.com
License: UNKNOWN
Platform: UNKNOWN
Requires-Python: >=3.6
Requires-Dist: numpy
Requires-Dist: scipy
Requires-Dist: matplotlib
Requires-Dist: pathlib
Requires-Dist: pydeepl
